bolib3/__init__.py
bolib3-3.0.1.dist-info/METADATA
bolib3-3.0.1.dist-info/WHEEL
bolib3-3.0.1.dist-info/licenses/LICENSE.txt
bolib3-3.0.1.dist-info/RECORD
