Metadata-Version: 2.4
Name: bolib3
Version: 3.0.1
Summary: Welcome to BOLIB3, a benchmarking library of continuous bilevel optimization problems.
Project-URL: homepage, https://www.bolib.org/
Author-email: Samuel Ward <samuelwarda1@gmail.com>
License: Copyright (c) 2025, Samuel Ward.
License-File: LICENSE.txt
Classifier: License :: OSI Approved :: BSD License
Classifier: Operating System :: OS Independent
Classifier: Programming Language :: Python :: 3
Requires-Python: >=3.11
